onelogin/__init__.py
onelogin/saml2/__init__.py
onelogin/saml2/auth.py
onelogin/saml2/authn_request.py
onelogin/saml2/compat.py
onelogin/saml2/constants.py
onelogin/saml2/errors.py
onelogin/saml2/idp_metadata_parser.py
onelogin/saml2/logout_request.py
onelogin/saml2/logout_response.py
onelogin/saml2/metadata.py
onelogin/saml2/response.py
onelogin/saml2/settings.py
onelogin/saml2/utils.py
onelogin/saml2/xml_templates.py
onelogin/saml2/xml_utils.py
onelogin/saml2/xmlparser.py
onelogin/saml2/schemas/saml-schema-assertion-2.0.xsd
onelogin/saml2/schemas/saml-schema-authn-context-2.0.xsd
onelogin/saml2/schemas/saml-schema-authn-context-types-2.0.xsd
onelogin/saml2/schemas/saml-schema-metadata-2.0.xsd
onelogin/saml2/schemas/saml-schema-protocol-2.0.xsd
onelogin/saml2/schemas/sstc-metadata-attr.xsd
onelogin/saml2/schemas/sstc-saml-attribute-ext.xsd
onelogin/saml2/schemas/sstc-saml-metadata-algsupport-v1.0.xsd
onelogin/saml2/schemas/sstc-saml-metadata-ui-v1.0.xsd
onelogin/saml2/schemas/xenc-schema.xsd
onelogin/saml2/schemas/xml.xsd
onelogin/saml2/schemas/xmldsig-core-schema.xsd
python3_saml-1.16.0.dist-info/LICENSE
python3_saml-1.16.0.dist-info/METADATA
python3_saml-1.16.0.dist-info/WHEEL
python3_saml-1.16.0.dist-info/dependency_links.txt
python3_saml-1.16.0.dist-info/top_level.txt
python3_saml-1.16.0.dist-info/RECORD
